[{"broker_id":"default","symbol":"HK33HKD","bid":26389.4,"ask":26399.4,"spread":1000000,"timestamp":"2026-01-03T17:44:13.199134+05:30","lp":"OANDA"},{"broker_id":"default","symbol":"HK33HKD","bid":26389.4,"ask":26399.4,"spread":1000000,"timestamp":"2026-01-03T17:48:40.232242+05:30","lp":"OANDA"},{"broker_id":"default","symbol":"HK33HKD","bid":26389.4,"ask":26399.4,"spread":1000000,"timestamp":"2026-01-03T18:30:48.103853+05:30","lp":"OANDA"},{"broker_id":"default","symbol":"HK33HKD","bid":26389.4,"ask":26399.4,"spread":1000000,"timestamp":"2026-01-03T18:34:18.955152+05:30","lp":"OANDA"},{"broker_id":"default","symbol":"HK33HKD","bid":26389.4,"ask":26399.4,"spread":1000000,"timestamp":"2026-01-03T18:38:51.306405+05:30","lp":"OANDA"},{"broker_id":"default","symbol":"HK33HKD","bid":26389.4,"ask":26399.4,"spread":1000000,"timestamp":"2026-01-03T18:42:07.307467+05:30","lp":"OANDA"},{"broker_id":"default","symbol":"HK33HKD","bid":26389.4,"ask":26399.4,"spread":1000000,"timestamp":"2026-01-03T18:43:18.660228+05:30","lp":"OANDA"},{"broker_id":"default","symbol":"HK33HKD","bid":26389.4,"ask":26399.4,"spread":1000000,"timestamp":"2026-01-03T18:44:44.931758+05:30","lp":"OANDA"},{"broker_id":"default","symbol":"HK33HKD","bid":26389.4,"ask":26399.4,"spread":1000000,"timestamp":"2026-01-03T18:46:30.954296+05:30","lp":"OANDA"},{"broker_id":"default","symbol":"HK33HKD","bid":26389.4,"ask":26399.4,"spread":1000000,"timestamp":"2026-01-03T18:50:16.903751+05:30","lp":"OANDA"},{"broker_id":"default","symbol":"HK33HKD","bid":26389.4,"ask":26399.4,"spread":1000000,"timestamp":"2026-01-03T18:54:08.578699+05:30","lp":"OANDA"},{"broker_id":"default","symbol":"HK33HKD","bid":26389.4,"ask":26399.4,"spread":1000000,"timestamp":"2026-01-03T19:00:18.451378+05:30","lp":"OANDA"},{"broker_id":"default","symbol":"HK33HKD","bid":26389.4,"ask":26399.4,"spread":1000000,"timestamp":"2026-01-03T19:03:38.007838+05:30","lp":"OANDA"}]