[{"broker_id":"default","symbol":"XAUNZD","bid":7506.103,"ask":7511.103,"spread":500,"timestamp":"2026-01-03T17:44:13.145884+05:30","lp":"OANDA"},{"broker_id":"default","symbol":"XAUNZD","bid":7506.103,"ask":7511.103,"spread":500,"timestamp":"2026-01-03T17:48:40.231788+05:30","lp":"OANDA"},{"broker_id":"default","symbol":"XAUNZD","bid":7506.103,"ask":7511.103,"spread":500,"timestamp":"2026-01-03T18:30:48.082158+05:30","lp":"OANDA"},{"broker_id":"default","symbol":"XAUNZD","bid":7506.103,"ask":7511.103,"spread":500,"timestamp":"2026-01-03T18:34:18.939777+05:30","lp":"OANDA"},{"broker_id":"default","symbol":"XAUNZD","bid":7506.103,"ask":7511.103,"spread":500,"timestamp":"2026-01-03T18:38:51.257709+05:30","lp":"OANDA"},{"broker_id":"default","symbol":"XAUNZD","bid":7506.103,"ask":7511.103,"spread":500,"timestamp":"2026-01-03T18:42:07.294531+05:30","lp":"OANDA"},{"broker_id":"default","symbol":"XAUNZD","bid":7506.103,"ask":7511.103,"spread":500,"timestamp":"2026-01-03T18:43:18.651401+05:30","lp":"OANDA"},{"broker_id":"default","symbol":"XAUNZD","bid":7506.103,"ask":7511.103,"spread":500,"timestamp":"2026-01-03T18:44:44.885551+05:30","lp":"OANDA"},{"broker_id":"default","symbol":"XAUNZD","bid":7506.103,"ask":7511.103,"spread":500,"timestamp":"2026-01-03T18:46:30.808466+05:30","lp":"OANDA"},{"broker_id":"default","symbol":"XAUNZD","bid":7506.103,"ask":7511.103,"spread":500,"timestamp":"2026-01-03T18:50:16.885044+05:30","lp":"OANDA"},{"broker_id":"default","symbol":"XAUNZD","bid":7506.103,"ask":7511.103,"spread":500,"timestamp":"2026-01-03T18:54:08.578125+05:30","lp":"OANDA"},{"broker_id":"default","symbol":"XAUNZD","bid":7506.103,"ask":7511.103,"spread":500,"timestamp":"2026-01-03T19:00:18.425785+05:30","lp":"OANDA"},{"broker_id":"default","symbol":"XAUNZD","bid":7506.103,"ask":7511.103,"spread":500,"timestamp":"2026-01-03T19:03:38.006552+05:30","lp":"OANDA"}]